pdfocrer/__init__.py
pdfocrer/pdf_ocrer.py
pdfocrer/pdf_util.py
src/__init__.py
src/pdf_ocrer.py
src/pdf_util.py
tests/__init__.py
tests/test.py
PdfOCRer-1.2.dist-info/LICENSE
PdfOCRer-1.2.dist-info/METADATA
PdfOCRer-1.2.dist-info/WHEEL
PdfOCRer-1.2.dist-info/top_level.txt
PdfOCRer-1.2.dist-info/RECORD
