Metadata-Version: 2.1
Name: PdfOCRer
Version: 1.2
Summary: A Python script that runs Paddle OCR on a possibly unsearchable PDF to make it searchable. 
Home-page: https://github.com/msmarkgu/PdfOCRer
Author: Mark Gu
Author-email: mark.reachee@gmail.com
Classifier: Programming Language :: Python :: 3
Classifier: License :: OSI Approved :: MIT License
Classifier: Operating System :: OS Independent
Requires-Python: >=3.8
License-File: LICENSE
Requires-Dist: pypdf2
Requires-Dist: pillow
Requires-Dist: reportlab
Requires-Dist: paddleocr
Requires-Dist: paddlepaddle
